stopp/__init__.py
stopp/data_structs.py
stopp/joint_profile.py
stopp/stopp.py
stopp/trajectory_phases.py
stopp/trajectory_profiles.py
stopp/trajectory_utils.py
stopp-0.4.dist-info/LICENSE
stopp-0.4.dist-info/METADATA
stopp-0.4.dist-info/WHEEL
stopp-0.4.dist-info/top_level.txt
stopp-0.4.dist-info/RECORD
