Metadata-Version: 2.1
Name: stopp
Version: 0.4
Summary: Safe Time Optimal Path Parametrization (STOPP) for serial robots
Home-page: https://github.com/AbdelrhmanBassiouny/stopp
Download-URL: https://github.com/AbdelrhmanBassiouny/stopp/archive/v_03.tar.gz
Author: Abdelrhman Bassiouny
Author-email: Bassio@programmer.com
License: MIT
Keywords: robot trajectory,safe,jerk limited,moveit path support
Classifier: Development Status :: 4 - Beta
Classifier: Intended Audience :: Developers
Classifier: Topic :: Software Development :: Build Tools
Classifier: License :: OSI Approved :: MIT License
Classifier: Programming Language :: Python
License-File: LICENSE
Requires-Dist: numpy (>=1.12.0)
